Workbook

Sheet INDICE
A1: INDICE
A3: FERRETERÍA | B3: página 1-2-3
A5: CONDUCTORES DE COBRE MH- CABLES VARIOS-CONECTORES- BORNERAS - CINTAS | B5: página 4-5-6-7-8-9
A7: JELUZ | B7: página 10-11-12-13
A9: CAJAS CAPSULADAS, BASES Y FICHAS INDUSTRIALES, FICHAS VARIAS Y PROLONGADORES (MIG-SICA-TOP-RICHI) | B9: página 14-15-16-17
A11: KALOP | B11: página 18-19-20-21
A13: GEN ROD | B13: página 22-23-24-25
A15: ABRAZADERAS, CAJAS Y CAÑOS METÁLICOS, CAÑOS PILAR | B15: página 26-27
A17: CAJAS Y GABINETES METÁLICOS - LÍNEA TAAD | B17: página 28
A19: CHINT | B19: página 29
A21: ARTICULOS VARIOS | B21: página 30-31
A23: LÁMPARAS E ILUMINACIÓN | B23: página 32-33-34-35-36-37

Sheet Catalogo Lista
A1: LISTA JULIO Nº 5
D4: DISCOS DIAMANTADOS
C6: 1930 | D6: DISCO DIAMANTADO ALIAFOR TRF 4,5¨ ( TURBO FINO ) | E6: =VLOOKUP(C6,'Precios Dotar'!$A:$E,5,FALSE) -> 19446.113 | F6: =E6*1.21*1.7 -> 40000.655
F7: =E7*1.21*1.7 -> 0
F8: =E8*1.21*1.7 -> 0
F9: =E9*1.21*1.7 -> 0
F10: =E10*1.21*1.7 -> 0
F11: =E11*1.21*1.7 -> 0
F12: =E12*1.21*1.7 -> 0
D13: PRECIOS DE LAS PILAS UNITARIOS | F13: =E13*1.21*1.7 -> 0
F14: =E14*1.21*1.7 -> 0
C15: 202 | D15: PILA "AA" BL X4 POWERSWICH-MACROLED | E15: =VLOOKUP(C15,'Precios Dotar'!$A:$E,5,FALSE) -> 502.07063 | F15: =E15*1.21*1.7 -> 1032.7593
C16: 204 | D16: PILA "AAA" BL X 4 POWERSWITCH-MACROLED | E16: =VLOOKUP(C16,'Precios Dotar'!$A:$E,5,FALSE) -> 391.86 | F16: =E16*1.21*1.7 -> 806.05602
F17: =E17*1.21*1.7 -> 0
F18: =E18*1.21*1.7 -> 0
C19: 201 | D19: PILA ENERGIZER E91 "AA" BLISTER X20 | E19: =VLOOKUP(C19,'Precios Dotar'!$A:$E,5,FALSE) -> 989.66868 | F19: =E19*1.21*1.7 -> 2035.7485
C20: 203 | D20: PILA ENERGIZER E92 "AAA" BLISTER X20 | E20: =VLOOKUP(C20,'Precios Dotar'!$A:$E,5,FALSE) -> 989.66868 | F20: =E20*1.21*1.7 -> 2035.7485
F21: =E21*1.21*1.7 -> 0
C22: 208 | D22: PILA ENERGIZER "C" Mediana BLISTER X2 | E22: =VLOOKUP(C22,'Precios Dotar'!$A:$E,5,FALSE) -> 4136.222 | F22: =E22*1.21*1.7 -> 8508.2086
F23: =E23*1.21*1.7 -> 0
C24: 209 | D24: PILA ENERGIZER "D" Grande BLISTER X2 | E24: =VLOOKUP(C24,'Precios Dotar'!$A:$E,5,FALSE) -> 5474.8508 | F24: =E24*1.21*1.7 -> 11261.768
F25: =E25*1.21*1.7 -> 0
C26: 205 | D26: BATERIA ENERGIZER 9V. 522 | E26: =VLOOKUP(C26,'Precios Dotar'!$A:$E,5,FALSE) -> 7018.986 | F26: =E26*1.21*1.7 -> 14438.054
F27: =E27*1.21*1.7 -> 0
C28: 27820 | D28: BATERIA 9V. POWERSWITCH-MACROLED | E28: =VLOOKUP(C28,'Precios Dotar'!$A:$E,5,FALSE) -> 1961.7491 | F28: =E28*1.21*1.7 -> 4035.318
F29: =E29*1.21*1.7 -> 0
C30: PILAS PARA AUDÍFONOS | F30: =E30*1.21*1.7 -> 0
F31: =E31*1.21*1.7 -> 0
C32: 10204 | D32: PILA PARA AUDIFONO AZ675 BLISTER X4 | E32: =VLOOKUP(C32,'Precios Dotar'!$A:$E,5,FALSE) -> 2090.5367 | F32: =E32*1.21*1.7 -> 4300.234
F33: =E33*1.21*1.7 -> 0
C34: 10203 | D34: PILA PARA AUDIFONO AZ13 BLISTER X4 | E34: =VLOOKUP(C34,'Precios Dotar'!$A:$E,5,FALSE) -> 2026.1223 | F34: =E34*1.21*1.7 -> 4167.7335
F35: =E35*1.21*1.7 -> 0
C36: 210 | D36: PILA PARA AUDIFONO AZ312 BLISTER X4 | E36: =VLOOKUP(C36,'Precios Dotar'!$A:$E,5,FALSE) -> 1776.1616 | F36: =E36*1.21*1.7 -> 3653.5645
F37: =E37*1.21*1.7 -> 0
C38: 10202 | D38: PILA PARA AUDIFONO AZ10 BLISTER X4 | E38: =VLOOKUP(C38,'Precios Dotar'!$A:$E,5,FALSE) -> 1558.5556 | F38: =E38*1.21*1.7 -> 3205.9488
F39: =E39*1.21*1.7 -> 0
C40: BATERIAS MINIATURA Y BOTON PARA ELECTRÓNICA | F40: =E40*1.21*1.7 -> 0
F41: =E41*1.21*1.7 -> 0
C42: 206 | D42: PILA ENERGIZER "A23" BLISTER X5 | E42: =VLOOKUP(C42,'Precios Dotar'!$A:$E,5,FALSE) -> 1867.108 | F42: =E42*1.21*1.7 -> 3840.6412
F43: =E43*1.21*1.7 -> 0
C44: 207 | D44: PILA ENERGIZER "A27" BLISTER X1 | E44: =VLOOKUP(C44,'Precios Dotar'!$A:$E,5,FALSE) -> 2802.7725 | F44: =E44*1.21*1.7 -> 5765.303
F45: =E45*1.21*1.7 -> 0
C46: 10205 | D46: PILA ECR 2016 BW BLISTER X5 | E46: =VLOOKUP(C46,'Precios Dotar'!$A:$E,5,FALSE) -> 1216.3878 | F46: =E46*1.21*1.7 -> 2502.1096
F47: =E47*1.21*1.7 -> 0
C48: 10206 | D48: PILA ECR 2025 SG BW BLISTER X5 | E48: =VLOOKUP(C48,'Precios Dotar'!$A:$E,5,FALSE) -> 1216.3878 | F48: =E48*1.21*1.7 -> 2502.1096
F49: =E49*1.21*1.7 -> 0
C50: 27802 | D50: PILA CR-2025 BL X 5 POWERSWITCH-MACROLED | E50: =VLOOKUP(C50,'Precios Dotar'!$A:$E,5,FALSE) -> 306.14062 | F50: =E50*1.21*1.7 -> 629.73127
F51: =E51*1.21*1.7 -> 0
F52: =E52*1.21*1.7 -> 0
F53: =E53*1.21*1.7 -> 0
F54: =E54*1.21*1.7 -> 0
C55: 10207 | D55: PILA ECR 2032 BW BLISTER X5 ENERGIZER | E55: =VLOOKUP(C55,'Precios Dotar'!$A:$E,5,FALSE) -> 1216.3878 | F55: =E55*1.21*1.7 -> 2502.1096
F56: =E56*1.21*1.7 -> 0
C57: 200 | D57: PILA CR-2032 CANDELA | E57: =VLOOKUP(C57,'Precios Dotar'!$A:$E,5,FALSE) -> 299.56576 | F57: =E57*1.21*1.7 -> 616.20677
F58: =E58*1.21*1.7 -> 0
C59: 27803 | D59: PILA CR-2032 BL X 5 POWERSWITCH-MACROLED | E59: =VLOOKUP(C59,'Precios Dotar'!$A:$E,5,FALSE) -> 306.14062 | F59: =E59*1.21*1.7 -> 629.73127
F60: =E60*1.21*1.7 -> 0
F61: =E61*1.21*1.7 -> 0
F62: =E62*1.21*1.7 -> 0
F63: =E63*1.21*1.7 -> 0
F64: =E64*1.21*1.7 -> 0
F65: =E65*1.21*1.7 -> 0
C66: 10365 | D66: PILA EVEREADY "C" Mediana BLISTER X2 | E66: =VLOOKUP(C66,'Precios Dotar'!$A:$E,5,FALSE) -> 1523.451 | F66: =E66*1.21*1.7 -> 3133.7387
F67: =E67*1.21*1.7 -> 0
C68: 10366 | D68: PILA "D" LR20 BL X 2 POWERSWITCH-MACROLED | E68: =VLOOKUP(C68,'Precios Dotar'!$A:$E,5,FALSE) -> 2412.3881 | F68: =E68*1.21*1.7 -> 4962.2824
F69: =E69*1.21*1.7 -> 0
F70: =E70*1.21*1.7 -> 0
D72: HERRAMIENTAS
C75: 18837 | D75: MULTITESTER DIGITAL SI-T830 SIWAY | E75: =VLOOKUP(C75,'Precios Dotar'!$A:$E,5,FALSE) -> 5212.8421
C78: 18838 | D78: PINZA AMPEROMETRICA SI-P266 SIWAY | E78: =VLOOKUP(C78,'Precios Dotar'!$A:$E,5,FALSE) -> 11204.366
D82: SOLDADORES
C84: 1953 | D84: SOLDADOR DE ESTAÑO 30W PTA. LAPIZ | E84: =VLOOKUP(C84,'Precios Dotar'!$A:$E,5,FALSE) -> 8197.789
C86: 1954 | D86: SOLDADOR DE ESTAÑO 40W. PTA LAPIZ | E86: =VLOOKUP(C86,'Precios Dotar'!$A:$E,5,FALSE) -> 8487.6316
D91: AGUA
C93: 27707 | D93: CANILLA 1/2 PVC GRIS (1765) | E93: =VLOOKUP(C93,'Precios Dotar'!$A:$E,5,FALSE) -> 1094.6902 | F93: =E93*1.21*1.7 -> 2251.7777
F94: =E94*1.21*1.7 -> 0
F95: =E95*1.21*1.7 -> 0
C96: 27759 | D96: CANILLA ESFÉRICA METÁLICA 1/2" (2728) | E96: =VLOOKUP(C96,'Precios Dotar'!$A:$E,5,FALSE) -> 3229.3546 | F96: =E96*1.21*1.7 -> 6642.7824
F97: =E97*1.21*1.7 -> 0
F98: =E98*1.21*1.7 -> 0
C99: 27769 | D99: RESISTENCIA Y TERMOSTATO 1500W (4065) | E99: =VLOOKUP(C99,'Precios Dotar'!$A:$E,5,FALSE) -> 18445.784 | F99: =E99*1.21*1.7 -> 37942.978
D107: TERMOS KOVEA
C109: 294 | D109: TERMO BLACK STONE CON PICO VERTEDOR 1 LT KOVEA | E109: SIN STOCK
C110: 293 | D110: TERMO BLACK STONE CON PICO VERTEDOR 0,75 LT KOVEA | E110: =VLOOKUP(C110,'Precios Dotar'!$A:$E,5,FALSE) -> 32037.999 | F110: =E110*1.21*1.7 -> 65902.164
C111: 292 | D111: TERMO BLACK STONE CON PICO VERTEDOR 0,50 LT KOVEA | E111: =VLOOKUP(C111,'Precios Dotar'!$A:$E,5,FALSE) -> 30290.472 | F111: =E111*1.21*1.7 -> 62307.5
F112: =E112*1.21*1.7 -> 0
F113: =E113*1.21*1.7 -> 0
F114: =E114*1.21*1.7 -> 0
C115: 2051 | D115: TAPÓN TERMO CEBADOR 0,50-0,75 Y 1 LT. KOVEA | E115: =VLOOKUP(C115,'Precios Dotar'!$A:$E,5,FALSE) -> 8638.11 | F115: =E115*1.21*1.7 -> 17768.592
D119: GAS
C121: 2044 | D121: REGULADOR de GAS CABEZA P/10 KG Azul | E121: =VLOOKUP(C121,'Precios Dotar'!$A:$E,5,FALSE) -> 6134.31 | F121: =E121*1.21*1.7 -> 12618.276
F122: =E122*1.21*1.7 -> 0
F123: =E123*1.21*1.7 -> 0
C124: 2045 | D124: REGULADOR GAS X 1 M. | E124: =VLOOKUP(C124,'Precios Dotar'!$A:$E,5,FALSE) -> 8012.16 | F124: =E124*1.21*1.7 -> 16481.013
F125: =E125*1.21*1.7 -> 0
F126: =E126*1.21*1.7 -> 0
C127: 2048 | D127: REGULADOR GAS X 1.5 M | E127: =VLOOKUP(C127,'Precios Dotar'!$A:$E,5,FALSE) -> 9138.87 | F127: =E127*1.21*1.7 -> 18798.656
F128: =E128*1.21*1.7 -> 0
F129: =E129*1.21*1.7 -> 0
C130: 1993 | D130: SOPLETE MULTIPROPOSITO CARTUCHO GAS C/ENC .ELEC.BROGAS | E130: SIN STOCK | F130: =E130*1.21*1.7 -> #VALUE!
...

Sheet Precios Dotar
A1: Codigo | B1: Descripcion | C1: Lista 4 s/IVA | D1: Moneda | E1: 1555
A2: 5 | B2: PROTECTOR DE TENSION 2P. 40A | C2: 19.594009 | D2: Dolares | E2: =IF(D2="Dolares",C2*$E$1,C2) -> 30468.683
A3: 6 | B3: PROTECTOR PARA TOMAS (PONCHITO) BOLSA X10 KALOP | C3: 1682.8993 | D3: Pesos Argentinos | E3: =IF(D3="Dolares",C3*$E$1,C3) -> 1682.8993
A4: 7 | B4: PROTECTOR RED TRIFASICA DIRECTA 63A DIN BAW | C4: 92.688247 | D4: Dolares | E4: =IF(D4="Dolares",C4*$E$1,C4) -> 144130.22
A5: 9 | B5: CERRADURA ELECTRICA CABRERA | C5: 18360.477 | D5: Pesos Argentinos | E5: =IF(D5="Dolares",C5*$E$1,C5) -> 18360.477
A6: 10 | B6: FUENTE ALIMENTACION REGULADA VOLTAJE 12 V. COMMAX | C6: 61.204 | D6: Dolares | E6: =IF(D6="Dolares",C6*$E$1,C6) -> 95172.22
A7: 11 | B7: TRAFO CON PULSADOR P/CERRADURA ELEC. CABRERA | C7: 23417.485 | D7: Pesos Argentinos | E7: =IF(D7="Dolares",C7*$E$1,C7) -> 23417.485
A8: 12 | B8: FRENTE DE CALLE DE 10 TELEFONOS COMMAX | C8: 168.311 | D8: Dolares | E8: =IF(D8="Dolares",C8*$E$1,C8) -> 261723.61
A9: 13 | B9: FRENTE EXPANDER 10 PULS. LARGO COMMAX | C9: 119.626 | D9: Dolares | E9: =IF(D9="Dolares",C9*$E$1,C9) -> 186018.43
A10: 14 | B10: FRENTE EXPANDER 6 PULS LARGO COMMAX | C10: 95.979 | D10: Dolares | E10: =IF(D10="Dolares",C10*$E$1,C10) -> 149247.35
A11: 15 | B11: FRENTE EXPANDER 8 PULS. LARGO COMMAX | C11: 108.498 | D11: Dolares | E11: =IF(D11="Dolares",C11*$E$1,C11) -> 168714.39
A12: 16 | B12: FRENTE PORTERO PARA 12 TELEFONOS COMMAX | C12: 176.657 | D12: Dolares | E12: =IF(D12="Dolares",C12*$E$1,C12) -> 274701.64
A13: 17 | B13: FRENTE PORTERO PARA 2 TELEFONOS COMMAX | C13: 94.588 | D13: Dolares | E13: =IF(D13="Dolares",C13*$E$1,C13) -> 147084.34
... A4681: 27891 | B4681: BOBINA NXC-06 380V CHINT | C4681: 5.903625 | D4681: Dolares | E4681: =IF(D4681="Dolares",C4681*$E$1,C4681) -> 9180.1369

Sheet Novedades
A1: NOVEDADES DICIEMBRE
A7: DETECTOR DE TENSION BAW
A9: 804.34 | B9: Detector de tensión sin contacto directo Marca BAW. Electrónico tipo lapicera. Indicación luminosa y sonora (2 en 1). Rango de detección de tensión: 90~1000Vca, sensibilidad 4mm. Equipado con práctica linterna LED. Norma IEC 61010-1. Emplea 2 baterías de 1,5V AAA (no provistas) con una duración de hasta 6 horas en forma continua y más de 1 año en standby
A11: NUEVA LINEA DE PRODUCTOS: ROKER (Pag. 18) | B11: PRODUCTOS ROKER
A25: PROLONGADOR MULTIPLE 4 TOMAS CON CABLE
A27: 8954 | B27: PROLONGADOR 4 TOMAS MULTINORMA - INT. COMUN - CABLE 1,5 m | G27: =VLOOKUP(A27,#REF!,4,FALSE) -> #REF!
A28: 8955 | B28: PROLONGADOR 4 TOMAS MULTINORMA - INT. COMUN - CABLE 2,5 m | G28: =VLOOKUP(A28,#REF!,4,FALSE) -> #REF!
A29: 8956 | B29: PROLONGADOR 4 TOMAS MULTINORMA - INT. COMUN - CABLE 5,0 m | G29: =VLOOKUP(A29,#REF!,4,FALSE) -> #REF!
A31: LISTON BAJO ALACENA LED
A32: 8925 | B32: LISTON 9W LUZ DIA 600 mm. | G32: =VLOOKUP(A32,#REF!,4,FALSE) -> #REF!
A33: 8926 | B33: LISTON 14W LUZ DIA 900 mm. | G33: =VLOOKUP(A33,#REF!,4,FALSE) -> #REF!
A34: 8927 | B34: LISTON 18W LUZ DIA 1200 mm. | G34: =VLOOKUP(A34,#REF!,4,FALSE) -> #REF!
A36: MEDIDORES DE CONSUMO MONOFASICO / TRIFASICO
A37: 8284 | B37: MEDIDOR DIGITAL MONOFASICO P/DIN | G37: =VLOOKUP(A37,#REF!,4,FALSE) -> #REF!
A38: 8945 | B38: MEDIDOR DIGITAL MONOFASICO P/DIN CON PUESTA A 0 PARCIAL | G38: =VLOOKUP(A38,#REF!,4,FALSE) -> #REF!
A39: 8285 | B39: MEDIDOR DIGITAL TRIFASICO P/DIN | G39: =VLOOKUP(A39,#REF!,4,FALSE) -> #REF!
A43: Precios de lista mas IVA no incluye descuentos

Sheet Hoja1

Sheet Hoja2

Sheet Hoja3
